LICENSE.txt
MANIFEST.in
README.md
VERSION
requirements.txt
setup.cfg
setup.py
bin/panther_analysis_tool
bin/pat
panther_analysis_tool/__init__.py
panther_analysis_tool/analysis_utils.py
panther_analysis_tool/cli_output.py
panther_analysis_tool/constants.py
panther_analysis_tool/destination.py
panther_analysis_tool/directory.py
panther_analysis_tool/enriched_event.py
panther_analysis_tool/enriched_event_generator.py
panther_analysis_tool/immutable.py
panther_analysis_tool/main.py
panther_analysis_tool/schema_regexs.py
panther_analysis_tool/schemas.py
panther_analysis_tool/testing.py
panther_analysis_tool/util.py
panther_analysis_tool/validation.py
panther_analysis_tool/zip_chunker.py
panther_analysis_tool.egg-info/PKG-INFO
panther_analysis_tool.egg-info/SOURCES.txt
panther_analysis_tool.egg-info/dependency_links.txt
panther_analysis_tool.egg-info/requires.txt
panther_analysis_tool.egg-info/top_level.txt
panther_analysis_tool/backend/__init__.py
panther_analysis_tool/backend/client.py
panther_analysis_tool/backend/errors.py
panther_analysis_tool/backend/lambda_client.py
panther_analysis_tool/backend/mocks.py
panther_analysis_tool/backend/public_api_client.py
panther_analysis_tool/backend/graphql/async_bulk_upload.graphql
panther_analysis_tool/backend/graphql/async_bulk_upload_status.graphql
panther_analysis_tool/backend/graphql/bulk_upload.graphql
panther_analysis_tool/backend/graphql/create_or_update_schema.graphql
panther_analysis_tool/backend/graphql/create_perf_test.graphql
panther_analysis_tool/backend/graphql/delete_detections.graphql
panther_analysis_tool/backend/graphql/delete_saved_queries.graphql
panther_analysis_tool/backend/graphql/feature_flags.graphql
panther_analysis_tool/backend/graphql/generate_enriched_event.graphql
panther_analysis_tool/backend/graphql/get_rule_body.graphql
panther_analysis_tool/backend/graphql/get_version.graphql
panther_analysis_tool/backend/graphql/introspection_query.graphql
panther_analysis_tool/backend/graphql/list_schemas.graphql
panther_analysis_tool/backend/graphql/metrics.graphql
panther_analysis_tool/backend/graphql/replay.graphql
panther_analysis_tool/backend/graphql/stop_replay.graphql
