Metadata-Version: 2.2
Name: panther_analysis_tool
Version: 0.57.0
Summary: Panther command line interface for writing, testing, and packaging policies/rules.
Home-page: https://github.com/panther-labs/panther_analysis_tool
Download-URL: https://github.com/panther-labs/panther_analysis_tool/archive/v0.57.0.tar.gz
Author: Panther Labs Inc
Author-email: pypi@runpanther.io
License: AGPL-3.0
Keywords: Security,CLI
Classifier: Development Status :: 4 - Beta
Classifier: Intended Audience :: Developers
Classifier: Topic :: Security
Classifier: License :: OSI Approved :: GNU Affero General Public License v3
Classifier: Programming Language :: Python :: 3.11
License-File: LICENSE.txt
Requires-Dist: gql
Requires-Dist: aiohttp
Requires-Dist: boto3
Requires-Dist: dynaconf
Requires-Dist: jsonpath-ng
Requires-Dist: jsonschema
Requires-Dist: nested_lookup
Requires-Dist: packaging
Requires-Dist: requests
Requires-Dist: ruamel.yaml
Requires-Dist: schema
Requires-Dist: semver
Requires-Dist: sqlfluff
Requires-Dist: panther-core==0.11.2
Requires-Dist: typing-extensions
Requires-Dist: jsonlines
Dynamic: author
Dynamic: author-email
Dynamic: classifier
Dynamic: description
Dynamic: description-content-type
Dynamic: download-url
Dynamic: home-page
Dynamic: keywords
Dynamic: license
Dynamic: requires-dist
Dynamic: summary
